AI_yolo_label_checker/AI_yolo_label_checker.py
AI_yolo_label_checker/AiLibs.py
AI_yolo_label_checker/__init__.py
AI_yolo_label_checker/cv2_pan_zoom.py
AI_yolo_label_checker/image_crop_labelled_yolo_images.py
AI_yolo_label_checker/IVIS_data/config.yml
AI_yolo_label_checker/IVIS_data/system.ta
AI_yolo_label_checker-2.7.1.dist-info/METADATA
AI_yolo_label_checker-2.7.1.dist-info/WHEEL
AI_yolo_label_checker-2.7.1.dist-info/entry_points.txt
AI_yolo_label_checker-2.7.1.dist-info/top_level.txt
AI_yolo_label_checker-2.7.1.dist-info/RECORD
