Metadata-Version: 2.1
Name: AI_yolo_label_checker
Version: 2.7.1
Summary: Thư viện hữu ích của Tuấn Anh.
Home-page: https://pypi.org/project/AI-yolo-label-checker/
Author: Tuấn Anh - Foxconn
Author-email: nt.anh.fai@gmail.com
License: MIT
Classifier: Programming Language :: Python :: 3
Classifier: License :: OSI Approved :: MIT License
Classifier: Operating System :: OS Independent
Requires-Dist: collection
Requires-Dist: matplotlib
Requires-Dist: numpy
Requires-Dist: opencv-python
